{
	"description": "Gets a list of managed clusters in the specified subscription. The operation returns properties of each managed cluster.",
	"input_method": "stdin",
	"parameters":{
		
		
		
		
		    
			"api_version":{
			   "description": "Client Api Version.",
			   "type": "Optional[String[1]]"
			}
			,
		    
			"subscription_id":{
			   "description": "Subscription credentials which uniquely identify Microsoft Azure subscription. The subscription ID forms part of the URI for every service call.",
			   "type": "Optional[String[1]]"
			}
			,
		    
			"value":{
			   "description": "The list of managed clusters.",
			   "type": "Optional[String[1]]"
			}
			,
		    
			"nextlink":{
			   "description": "The URL to get the next set of managed cluster results.",
			   "type": "Optional[String[1]]"
			}
			
	}
}