{
	"description": "Lists all of the available Media Services REST API operations.",
	"input_method": "stdin",
	"parameters":{
		
		
		
		
		    
			"api_version":{
			   "description": "Version of the API to be used with the client request. The current version is 2015-10-01.",
			   "type": "Optional[String[1]]"
			}
			,
		    
			"nextlink":{
			   "description": "URL to get the next set of operation list results if there are any.",
			   "type": "Optional[String[1]]"
			}
			,
		    
			"value":{
			   "description": "List of Media Services operations supported by the Microsoft.Media resource provider.",
			   "type": "Optional[String[1]]"
			}
			
	}
}