{
	"description": "Regenerates a primary or secondary key for a Media Service.",
	"input_method": "stdin",
	"parameters":{
		
		
		
		
		    
			"parameters":{
			   "description": "Properties needed to regenerate the Media Service key.",
			   "type": "Optional[String[1]]"
			}
			,
		    
			"keytype":{
			   "description": "The keyType indicating which key you want to regenerate, Primary or Secondary.",
			   "type": "Optional[String[1]]"
			}
			,
		    
			"subscription_id":{
			   "description": "The unique identifier for a Microsoft Azure subscription.",
			   "type": "Optional[String[1]]"
			}
			,
		    
			"api_version":{
			   "description": "Version of the API to be used with the client request. The current version is 2015-10-01.",
			   "type": "Optional[String[1]]"
			}
			,
		    
			"resource_group_name":{
			   "description": "Name of the resource group within the Azure subscription.",
			   "type": "Optional[String[1]]"
			}
			,
		    
			"media_service_name":{
			   "description": "Name of the Media Service.",
			   "type": "Optional[String[1]]"
			}
			
	}
}