{
	"description": "Delete a Power BI Workspace Collection.",
	"input_method": "stdin",
	"parameters":{
		
		
		
		
		    
			"target":{
			   "description": "",
			   "type": "Optional[String[1]]"
			}
			,
		    
			"details":{
			   "description": "",
			   "type": "Optional[String[1]]"
			}
			,
		    
			"subscription_id":{
			   "description": "Gets subscription credentials which uniquely identify a Microsoft Azure subscription. The subscription ID forms part of the URI for every service call.",
			   "type": "Optional[String[1]]"
			}
			,
		    
			"resource_group_name":{
			   "description": "Azure resource group",
			   "type": "Optional[String[1]]"
			}
			,
		    
			"workspace_collection_name":{
			   "description": "Power BI Embedded Workspace Collection name",
			   "type": "Optional[String[1]]"
			}
			,
		    
			"api_version":{
			   "description": "Client Api Version.",
			   "type": "Optional[String[1]]"
			}
			,
		    
			"code":{
			   "description": "",
			   "type": "Optional[String[1]]"
			}
			,
		    
			"message":{
			   "description": "",
			   "type": "Optional[String[1]]"
			}
			
	}
}