{
	"description": "Get available application frameworks and their versions",
	"input_method": "stdin",
	"parameters":{
		
		
		
		
		    
			"api_version":{
			   "description": "API Version",
			   "type": "Optional[String[1]]"
			}
			,
		    
			"display":{
			   "description": "Application stack display name.",
			   "type": "Optional[String[1]]"
			}
			,
		    
			"dependency":{
			   "description": "Application stack dependency.",
			   "type": "Optional[String[1]]"
			}
			,
		    
			"majorversions":{
			   "description": "List of major versions available.",
			   "type": "Optional[String[1]]"
			}
			,
		    
			"frameworks":{
			   "description": "List of frameworks associated with application stack.",
			   "type": "Optional[String[1]]"
			}
			,
		    
			"name":{
			   "description": "Application stack name.",
			   "type": "Optional[String[1]]"
			}
			,
		    
			"os_type_selected":{
			   "description": "",
			   "type": "Optional[String[1]]"
			}
			,
		    
			"subscription_id":{
			   "description": "Your Azure subscription ID. This is a GUID-formatted string (e.g. 00000000-0000-0000-0000-000000000000).",
			   "type": "Optional[String[1]]"
			}
			
	}
}