{
	"description": "Get specific `Reservation` details.",
	"input_method": "stdin",
	"parameters":{
		
		
		
		
		    
			"sku":{
			   "description": "",
			   "type": "Optional[String[1]]"
			}
			,
		    
			"reservation_id":{
			   "description": "Id of the Reservation Item",
			   "type": "Optional[String[1]]"
			}
			,
		    
			"api_version":{
			   "description": "Supported version.",
			   "type": "Optional[String[1]]"
			}
			,
		    
			"properties":{
			   "description": "",
			   "type": "Optional[String[1]]"
			}
			,
		    
			"type":{
			   "description": "Type of resource. 'Microsoft.Capacity/reservationOrders/reservations'",
			   "type": "Optional[String[1]]"
			}
			,
		    
			"etag":{
			   "description": "",
			   "type": "Optional[String[1]]"
			}
			,
		    
			"reservation_order_id":{
			   "description": "Order Id of the reservation",
			   "type": "Optional[String[1]]"
			}
			,
		    
			"location":{
			   "description": "",
			   "type": "Optional[String[1]]"
			}
			,
		    
			"id":{
			   "description": "Identifier of the reservation",
			   "type": "Optional[String[1]]"
			}
			,
		    
			"name":{
			   "description": "Name of the reservation",
			   "type": "Optional[String[1]]"
			}
			,
		    
			"kind":{
			   "description": "Resource Provider type to be reserved.",
			   "type": "Optional[String[1]]"
			}
			
	}
}