{
	"description": "Lists all of the available ServiceFabric REST API operations.",
	"input_method": "stdin",
	"parameters":{
		
		
		
		
		    
			"display":{
			   "description": "Display of the result",
			   "type": "Optional[String[1]]"
			}
			,
		    
			"origin":{
			   "description": "Origin result",
			   "type": "Optional[String[1]]"
			}
			,
		    
			"nextlink":{
			   "description": "The URL to use for getting the next set of results.",
			   "type": "Optional[String[1]]"
			}
			,
		    
			"api_version":{
			   "description": "The version of the ServiceFabric resource provider api",
			   "type": "Optional[String[1]]"
			}
			,
		    
			"name":{
			   "description": "Result name",
			   "type": "Optional[String[1]]"
			}
			
	}
}