{
	"description": "This API creates a batch of images from predicted images specified. There is a limit of 64 images and 20 tags.",
	"input_method": "stdin",
	"parameters":{
		
		
		
		
		    
			"training_key":{
			   "description": "API key.",
			   "type": "Optional[String[1]]"
			}
			,
		    
			"images":{
			   "description": "",
			   "type": "Optional[String[1]]"
			}
			,
		    
			"tagids":{
			   "description": "",
			   "type": "Optional[String[1]]"
			}
			,
		    
			"project_id":{
			   "description": "The project id.",
			   "type": "Optional[String[1]]"
			}
			,
		    
			"batch":{
			   "description": "Image and tag ids. Limited to 64 images and 20 tags per batch.",
			   "type": "Optional[String[1]]"
			}
			
	}
}